mjpeg_http_streamer/__init__.py
mjpeg_http_streamer/__main__.py
mjpeg_http_streamer/app.py
mjpeg_http_streamer/arguments.py
mjpeg_http_streamer/frame_broker.py
mjpeg_http_streamer/mjpeg_frame_reader.py
mjpeg_http_streamer/source.py
mjpeg_http_streamer/stream_provider.py
mjpeg_http_streamer-0.0.5.dist-info/LICENSE
mjpeg_http_streamer-0.0.5.dist-info/METADATA
mjpeg_http_streamer-0.0.5.dist-info/WHEEL
mjpeg_http_streamer-0.0.5.dist-info/top_level.txt
mjpeg_http_streamer-0.0.5.dist-info/RECORD
