Metadata-Version: 2.1
Name: mjpeg-http-streamer
Version: 0.0.5
Summary: A tool to create a http mjpeg stream from a plain mjpeg stream.
Home-page: https://github.com/andrekupka/mjpeg-http-streamer
Author: Andre Kupka
Author-email: me-github@andrekupka.de
License: UNKNOWN
Platform: UNKNOWN
Classifier: Programming Language :: Python :: 3
Classifier: License :: OSI Approved :: MIT License
Classifier: Operating System :: OS Independent
Requires-Python: >=3.6
License-File: LICENSE
Requires-Dist: aiohttp (>=3.8.1)
